{
  "schema_version": "1.0",
  "operation_id": "resume-submit-001",
  "experiment_id": "CAL001-F01-P1-R1",
  "command_type": "dreamina_text2video",
  "operation_kind": "submit",
  "started_at": "2026-07-18T18:33:03.086081Z",
  "completed_at": "2026-07-18T18:33:06.291614Z",
  "subprocess_exit_code": 0,
  "sanitized_stdout": "{\n  \"submit_id\": \"b1f101bb-cd4d-4fea-a12f-3437a09ab443\",\n  \"logid\": \"202607190233031692540470081946861\",\n  \"gen_status\": \"querying\",\n  \"credit_count\": 70\n}\n",
  "sanitized_stderr": "",
  "stdout_sha256": "e7e01c5662b42971ddd418dd42e76a8c3d611cf57adb07ee60dde1d493516cc5",
  "stderr_sha256": "e3b0c44298fc1c149afbf4c8996fb92427ae41e4649b934ca495991b7852b855",
  "hash_scope": "sanitized_utf8",
  "command_structure_without_prompt_or_secrets": [
    "C:/Users/msjpurf/bin/dreamina.exe",
    "text2video",
    "--model_version",
    "seedance2.0_vip",
    "--ratio",
    "16:9",
    "--prompt",
    "<redacted_prompt sha256=67ecc81b478cab5ca30b6ed9183dc52a29206dc3c7ce9e404f4b2fd3ce22cb88 chars=593>",
    "--duration",
    "5",
    "--video_resolution",
    "720p",
    "--poll",
    "0"
  ],
  "evidence_persisted_at": "2026-07-18T18:33:06.291614Z"
}
