{
  "schema_version": "1.0",
  "phase_id": "CAL-001-P3D-W01-F06-DIAG",
  "operation_id": "diagnostic-query-001",
  "query_index": 1,
  "experiment_id": "CAL001-F06-P1-R1",
  "existing_submit_id": "cabfa6ab-cc61-4d29-8630-da01dfdeef65",
  "subprocess_exit_code": 0,
  "returned_submit_id": "cabfa6ab-cc61-4d29-8630-da01dfdeef65",
  "gen_status": "querying",
  "queue_status": null,
  "fail_reason": null,
  "credit_count": null,
  "result_image_count": 0,
  "result_video_count": 0,
  "result_output_count": 0,
  "download_url_present": false,
  "sanitized_evidence_envelope_path": "experiments/CAL-001/execution_records/P3D_W01_DIAG/CAL001-F06-P1-R1/evidence/diagnostic-query-001.subprocess_envelope.json",
  "envelope_sha256": "0a9779e660b57f99e4618ae6ec2ebf4157e570b3f511f9861bc854fc60bbea2e",
  "no_download_dir": true,
  "download_count": 0,
  "retry_count": 0,
  "resubmit_count": 0,
  "parsed_at": "2026-07-18T20:27:20.419361Z"
}
